tokenexchangeauthenticator/__init__.py
tokenexchangeauthenticator/_version.py
tokenexchangeauthenticator/auth.py
tokenexchangeauthenticator/tests/__init__.py
tokenexchangeauthenticator/tests/conftest.py
tokenexchangeauthenticator/tests/mocks.py
tokenexchangeauthenticator/tests/test_auth.py
TokenExchangeAuthenticator-0.3.6.dist-info/METADATA
TokenExchangeAuthenticator-0.3.6.dist-info/WHEEL
TokenExchangeAuthenticator-0.3.6.dist-info/top_level.txt
TokenExchangeAuthenticator-0.3.6.dist-info/RECORD
