Metadata-Version: 2.1
Name: TokenExchangeAuthenticator
Version: 0.3.6
Summary: Jupyterhub oauth extension
Home-page: https://github.com/statisticsnorway/jupyterhub-extensions
Author: Statistics Norway
Author-email: bjorn.skaar@ssb.no
License: MIT
Keywords: JupyterHub,Authenticator,Statistics Norway
Platform: UNKNOWN
Classifier: License :: OSI Approved :: MIT License
Classifier: Intended Audience :: Developers
Classifier: Intended Audience :: Science/Research
Classifier: Programming Language :: Python
Classifier: Programming Language :: Python :: 3
Requires-Dist: jupyterhub >=3.0.0
Requires-Dist: oauthenticator >=15.1.0
Requires-Dist: pyjwt[crypto] >=2.4.0
